stac_model-0.5.0.dist-info/METADATA
stac_model-0.5.0.dist-info/WHEEL
stac_model-0.5.0.dist-info/entry_points.txt
stac_model-0.5.0.dist-info/licenses/LICENSE
stac_model/__init__.py
stac_model/__main__.py
stac_model/base.py
stac_model/examples.py
stac_model/input.py
stac_model/output.py
stac_model/runtime.py
stac_model/schema.py
stac_model/torch/__init__.py
stac_model/torch/base.py
stac_model/torch/export.py
stac_model/torch/utils.py
stac_model-0.5.0.dist-info/RECORD
