Metadata-Version: 2.1
Name: stac-model
Version: 0.5.0
Summary: A PydanticV2 validation and serialization libary for the STAC ML Model Extension
Keywords: STAC,SpatioTemporal Asset Catalog,Machine Learning Model,Artificial Intelligence
Author-Email: Ryan Avery <ryan@wherobots.com>, Francis Charette-Migneault <francis.charette-migneault@crim.ca>
License: Apache Software License 2.0
Classifier: Development Status :: 4 - Beta
Classifier: Operating System :: OS Independent
Classifier: Topic :: Software Development :: Libraries :: Python Modules
Classifier: License :: OSI Approved :: Apache Software License
Classifier: Programming Language :: Python :: 3
Classifier: Programming Language :: Python :: 3.10
Classifier: Programming Language :: Python :: 3.11
Classifier: Programming Language :: Python :: 3.12
Classifier: Programming Language :: Python :: 3.13
Classifier: Programming Language :: Python :: 3 :: Only
Classifier: Framework :: Pydantic
Classifier: Framework :: Pydantic :: 2
Classifier: Intended Audience :: Developers
Classifier: Intended Audience :: Information Technology
Classifier: Intended Audience :: Science/Research
Classifier: Topic :: File Formats :: JSON :: JSON Schema
Classifier: Topic :: Scientific/Engineering :: Artificial Intelligence
Classifier: Topic :: Scientific/Engineering :: GIS
Classifier: Topic :: Scientific/Engineering :: Image Processing
Classifier: Topic :: Scientific/Engineering :: Image Recognition
Project-URL: homepage, https://github.com/stac-extensions/mlm/blob/main/README_STAC_MODEL.md
Project-URL: repository, https://github.com/crim-ca/mlm-extension
Requires-Python: <4.0,>=3.10
Requires-Dist: typer<1.0.0,>=0.9.0
Requires-Dist: rich<15.0.0,>=13.7.0
Requires-Dist: pydantic<3.0.0,>=2.6.3
Requires-Dist: pydantic-core<3,>=2
Requires-Dist: pystac<2.0.0,>=1.9.0
Requires-Dist: shapely<3,>=2
Requires-Dist: jsonschema<5.0.0,>=4.21.1
Requires-Dist: pip>=25.0.0
Provides-Extra: torch
Requires-Dist: torch==2.8.0; python_version >= "3.11" and extra == "torch"
Requires-Dist: torchgeo; python_version >= "3.11" and extra == "torch"
Requires-Dist: torchvision<1,>=0.21; python_version >= "3.11" and extra == "torch"
Provides-Extra: torch-cu126
Requires-Dist: pytorch-triton; python_version >= "3.11" and extra == "torch-cu126"
Requires-Dist: torch==2.8.0; python_version >= "3.11" and extra == "torch-cu126"
Requires-Dist: torchgeo; python_version >= "3.11" and extra == "torch-cu126"
Requires-Dist: torchvision<1,>=0.21; python_version >= "3.11" and extra == "torch-cu126"
